nss3/__init__.py
nss3-4.5.16.dist-info/LICENSE
nss3-4.5.16.dist-info/METADATA
nss3-4.5.16.dist-info/WHEEL
nss3-4.5.16.dist-info/top_level.txt
nss3-4.5.16.dist-info/RECORD
