Metadata-Version: 2.1
Name: nss3
Version: 4.5.16
Summary: Simple and fast database operation
Home-page: https://pypi.org/
Author: Jingrui Zhu
Author-email: 870239526@qq.com
License: UNKNOWN
Platform: UNKNOWN
Classifier: Programming Language :: Python :: 3
Classifier: License :: OSI Approved :: MIT License
Classifier: Operating System :: OS Independent
